synapse_audiobomb_module/__init__.py
synapse_audiobomb_module/database.py
synapse_audiobomb_module-0.0.2.dist-info/LICENSE
synapse_audiobomb_module-0.0.2.dist-info/METADATA
synapse_audiobomb_module-0.0.2.dist-info/WHEEL
synapse_audiobomb_module-0.0.2.dist-info/top_level.txt
synapse_audiobomb_module-0.0.2.dist-info/RECORD
